hooks/__init__.py
hooks/interfaces.py
hooks/loader.py
hooks/models.py
hooks/run.py
hooks/runner.py
py_cursor_hooks-0.1.1.dist-info/licenses/LICENSE
py_cursor_hooks-0.1.1.dist-info/METADATA
py_cursor_hooks-0.1.1.dist-info/WHEEL
py_cursor_hooks-0.1.1.dist-info/top_level.txt
py_cursor_hooks-0.1.1.dist-info/RECORD
