Metadata-Version: 2.4
Name: py-cursor-hooks
Version: 0.1.1
Summary: A typed Python SDK for building Cursor hooks
Requires-Python: >=3.14
License-File: LICENSE
Requires-Dist: pydantic>=2.0
Provides-Extra: dev
Requires-Dist: pytest>=8; extra == "dev"
Requires-Dist: ruff>=0.8; extra == "dev"
Requires-Dist: mypy>=1.14; extra == "dev"
Requires-Dist: pre-commit>=4; extra == "dev"
Dynamic: license-file
